<?xml version="1.0" encoding="utf-8" ?>
<dwsync>
<file name="ScriptStyle.php" server="C:/xampp" local="130257839570000000" remote="130257839570000000" Dst="0" />
<file name="Footer.php" server="C:/xampp" local="130257825590000000" remote="130257825590000000" Dst="0" />
<file name="ScriptStyleView.php" server="C:/xampp" local="130257680760000000" remote="130257680760000000" Dst="0" />
<file name="Login.php" server="C:/xampp" local="130258546225439008" remote="130258546220000000" Dst="0" />
<file name="OuterHeader.php" server="C:/xampp" local="130258533150384299" remote="130258533150000000" Dst="0" />
<file name="index.php" server="C:/xampp" local="130259481220000000" remote="130259481220000000" Dst="0" />
<file name="Header.php" server="C:/xampp" local="130257662952343380" remote="130257662950000000" Dst="0" />
<file name="LeftMenu.php" server="C:/xampp" local="130256845210000000" remote="130256845210000000" Dst="0" />
<file name="CompanyDetails.php" server="C:/xampp" local="130254397118360380" remote="130254397110000000" Dst="0" />
<file name="OwnerDetails.php" server="C:/xampp" local="130252513264314620" remote="130252513260000000" Dst="0" />
<file name="Profile.php" server="C:/xampp" local="130253435046734400" remote="130253435040000000" Dst="0" />
<file name="Events.php" server="C:/xampp" local="130258727513370480" remote="130258727510000000" Dst="0" />
<file name="LogoUpload.php" server="C:/xampp" local="130258696938606547" remote="130258696930000000" Dst="0" />
<file name="Gallery.php" server="C:/xampp" local="130257069073918428" remote="130257069070000000" Dst="0" />
<file name="HeaderSet.php" server="C:/xampp" local="130257069549095993" remote="130257069540000000" Dst="0" />
<file name="Product.php" server="C:/xampp" local="130259477208952307" remote="130259477200000000" Dst="0" />
<file name="ContactInfo.php" server="C:/xampp" local="130256966015303930" remote="130256966010000000" Dst="0" />
<file name="ChangePassword.php" server="C:/xampp" local="130256960087709646" remote="130256960080000000" Dst="0" />
<file name="ManageProfile.php" server="C:/xampp" local="130259552410000000" remote="130259552410000000" Dst="0" />
<file name="ScriptStyleView.php" server="C:/xampp/" local="130269158809894329" remote="130269158800000000" Dst="0" />
<file name="ScriptStyle.php" server="C:/xampp/" local="130259659250000000" remote="130259659250000000" Dst="0" />
<file name="OuterHeader.php" server="C:/xampp/" local="130269167766417193" remote="130269167760000000" Dst="0" />
<file name="Footer.php" server="C:/xampp/" local="130257825590000000" remote="130257825590000000" Dst="0" />
<file name="Login.php" server="C:/xampp/" local="130263133580706705" remote="130263133580000000" Dst="0" />
<file name="ProfileFooter.php" server="C:/xampp/" local="130250938819941697" remote="130250938810000000" Dst="0" />
<file name="Advertisement.php" server="C:/xampp/" local="130269974419630279" remote="130269974410000000" Dst="0" />
<file name="boilerplate.css" server="C:/xampp/" local="129776522660000000" remote="129776522660000000" Dst="0" />
<file name="respond.min.js" server="C:/xampp/" local="129776522660000000" remote="129776522660000000" Dst="0" />
<file name="5513784476081.jpg" server="C:/xampp/" local="130344244473818662" remote="130344244470000000" Dst="0" />
<file name="T.html" server="C:/xampp/" local="130345157853393276" remote="130345157850000000" Dst="0" />
</dwsync>